christofy/__init__.py
christofy/ml.py
christofy/model_trainer.py
christofy/predictor.py
christofy/rag.py
christofy/segmentation.py
christofy/vision.py
christofy-1.0.2.dist-info/licenses/LICENSE
christofy-1.0.2.dist-info/METADATA
christofy-1.0.2.dist-info/WHEEL
christofy-1.0.2.dist-info/top_level.txt
christofy-1.0.2.dist-info/RECORD
