Metadata-Version: 2.4
Name: christofy
Version: 1.0.2
Summary: Christofy is a lightweight, modular PyTorch-based AI toolkit that unifies essential deep learning capabilities. It supports Image Classification, Segmentation, and advanced Vision Analysis with clean, easy-to-use APIs. With built-in Retrieval-Augmented Generation (RAG) powered by ChromaDB and Ollama, it seamlessly blends vision and language intelligence. Designed for flexibility and speed, Christofy is your all-in-one arsenal for building modern AI solutions.
Author-email: Aswin Christo <aswinchristo17@gmail.com>
License-Expression: MIT
Project-URL: Homepage, https://github.com/aswinchristo/christofy
Project-URL: Bug Tracker, https://github.com/aswinchristo/christofy/issues
Classifier: Programming Language :: Python :: 3
Classifier: Operating System :: OS Independent
Requires-Python: >=3.9
License-File: LICENSE
Dynamic: license-file
